{
  "indexes": [
    {
      "collectionGroup": "products",
      "queryScope": "COLLECTION",
      "fields": [
        {
          "fieldPath": "status",
          "order": "ASCENDING"
        },
        {
          "fieldPath": "publicStock",
          "order": "ASCENDING"
        }
      ]
    },
    {
      "collectionGroup": "product_variants",
      "queryScope": "COLLECTION",
      "fields": [
        {
          "fieldPath": "productId",
          "order": "ASCENDING"
        },
        {
          "fieldPath": "status",
          "order": "ASCENDING"
        },
        {
          "fieldPath": "sortOrder",
          "order": "ASCENDING"
        }
      ]
    },
    {
      "collectionGroup": "inventory_movements",
      "queryScope": "COLLECTION",
      "fields": [
        {
          "fieldPath": "productId",
          "order": "ASCENDING"
        },
        {
          "fieldPath": "occurredAt",
          "order": "DESCENDING"
        }
      ]
    },
    {
      "collectionGroup": "purchase_items",
      "queryScope": "COLLECTION",
      "fields": [
        {
          "fieldPath": "purchaseId",
          "order": "ASCENDING"
        },
        {
          "fieldPath": "purchasedAt",
          "order": "DESCENDING"
        }
      ]
    }
  ],
  "fieldOverrides": []
}
